FoxHustle_QR/QRCodeViewer.py
FoxHustle_QR/__init__.py
FoxHustle_QR/images/logotype_colored_dark.png
FoxHustle_QR/images/logotype_colored_light.png
FoxHustle_QR/images/logotype_mono_dark.png
FoxHustle_QR/images/logotype_mono_white.png
FoxHustle_QR-1.22.dist-info/LICENSE
FoxHustle_QR-1.22.dist-info/METADATA
FoxHustle_QR-1.22.dist-info/WHEEL
FoxHustle_QR-1.22.dist-info/top_level.txt
FoxHustle_QR-1.22.dist-info/RECORD
