Metadata-Version: 2.1
Name: FoxHustle-QR
Version: 1.22
Summary: QR-code Generator
Home-page: https://github.com/Fox-Hustle/QR-generator.git
Author: DmitryKang
Author-email: alexandrov.dp@mail.ru
License: MIT
Platform: UNKNOWN
Requires-Python: >=3.6
License-File: LICENSE
Requires-Dist: Pillow (==8.2.0)
Requires-Dist: PyQRCode (==1.2.1)
Requires-Dist: requests (==2.23.0)
